Workbook

Sheet Sheet2
B1: usuario | C1: empresa
A2: A | B2: pablo | C2: Servicios Agropecuarios Cuyo S.A.

Sheet general
A1: i_factura | B1: i_tipoFactura | C1: i_fecha | D1: i_numeroFactura | E1: i_cliente | F1: i_jurisdiccion | G1: i_tipoVenta | H1: i_mesFacturacion | I1: i_montoControl | J1: o_montoFacturado | K1: o_asiento
A2: SI | B2: Factura A Webservice | C2: 12/3/2026 | D2: 0003-00001690 | E2: GRANAR S.A.C y F. | F2: Mendoza | G2: Otras ventas | H2: FEBRERO | I2: 10372589 | J2: 10372589 | K2: 2026-VEN-264

Sheet Controles
A1: i_cliente | B1: controlTablas | C1: Fijo | D1: Variable | E1: Movilidad | F1: Recuperos | G1: Anticipos
A2: FOA AGUAS DE ALTAMIRA | B2: =+C2+D2+E2-G2+F2 | C2: =SUMIF(conceptoFijo!$A:$A,A2,conceptoFijo!$J:$J) | D2: =SUMIF(conceptoVariable!$A:$A,Controles!A2,conceptoVariable!$J:$J) | E2: =SUMIF(conceptoMovilidad!$A:$A,A2,conceptoMovilidad!$I:$I) | F2: =SUMIF(conceptoRecuperos!$B:$B,A2,conceptoRecuperos!$J:$J) | G2: =SUMIFS(conceptoAnticipos!$J:$J,conceptoAnticipos!$B:$B,Controles!A2,conceptoAnticipos!$A:$A,"SI")
A3: GRANAR S.A.C y F. (AB) | B3: =+C3+D3+E3-G3+F3 | C3: =SUMIF(conceptoFijo!$A:$A,A3,conceptoFijo!$J:$J) | D3: =SUMIF(conceptoVariable!$A:$A,Controles!A3,conceptoVariable!$J:$J) | E3: =SUMIF(conceptoMovilidad!$A:$A,A3,conceptoMovilidad!$I:$I) | F3: =SUMIF(conceptoRecuperos!$B:$B,A3,conceptoRecuperos!$J:$J) | G3: =SUMIFS(conceptoAnticipos!$J:$J,conceptoAnticipos!$B:$B,Controles!A3,conceptoAnticipos!$A:$A,"SI")
A4: CABALGANDO SAFI | B4: =+C4+D4+E4-G4+F4 | C4: =SUMIF(conceptoFijo!$A:$A,A4,conceptoFijo!$J:$J) | D4: =SUMIF(conceptoVariable!$A:$A,Controles!A4,conceptoVariable!$J:$J) | E4: =SUMIF(conceptoMovilidad!$A:$A,A4,conceptoMovilidad!$I:$I) | F4: =SUMIF(conceptoRecuperos!$B:$B,A4,conceptoRecuperos!$J:$J) | G4: =SUMIFS(conceptoAnticipos!$J:$J,conceptoAnticipos!$B:$B,Controles!A4,conceptoAnticipos!$A:$A,"SI")
A5: GRANAR S.A.C y F. | B5: =+C5+D5+E5-G5+F5 | C5: =SUMIF(conceptoFijo!$A:$A,A5,conceptoFijo!$J:$J) | D5: =SUMIF(conceptoVariable!$A:$A,Controles!A5,conceptoVariable!$J:$J) | E5: =SUMIF(conceptoMovilidad!$A:$A,A5,conceptoMovilidad!$I:$I) | F5: =SUMIF(conceptoRecuperos!$B:$B,A5,conceptoRecuperos!$J:$J) | G5: =SUMIFS(conceptoAnticipos!$J:$J,conceptoAnticipos!$B:$B,Controles!A5,conceptoAnticipos!$A:$A,"SI")
A6: FOI TERRUÑOS DE LOS ANDES | B6: =+C6+D6+E6-G6+F6 | C6: =SUMIF(conceptoFijo!$A:$A,A6,conceptoFijo!$J:$J) | D6: =SUMIF(conceptoVariable!$A:$A,Controles!A6,conceptoVariable!$J:$J) | E6: =SUMIF(conceptoMovilidad!$A:$A,A6,conceptoMovilidad!$I:$I) | F6: =SUMIF(conceptoRecuperos!$B:$B,A6,conceptoRecuperos!$J:$J) | G6: =SUMIFS(conceptoAnticipos!$J:$J,conceptoAnticipos!$B:$B,Controles!A6,conceptoAnticipos!$A:$A,"SI")
A7: FINCA LAS MAGDALENAS S. A. S. | B7: =+C7+D7+E7-G7+F7 | C7: =SUMIF(conceptoFijo!$A:$A,A7,conceptoFijo!$J:$J) | D7: =SUMIF(conceptoVariable!$A:$A,Controles!A7,conceptoVariable!$J:$J) | E7: =SUMIF(conceptoMovilidad!$A:$A,A7,conceptoMovilidad!$I:$I) | F7: =SUMIF(conceptoRecuperos!$B:$B,A7,conceptoRecuperos!$J:$J) | G7: =SUMIFS(conceptoAnticipos!$J:$J,conceptoAnticipos!$B:$B,Controles!A7,conceptoAnticipos!$A:$A,"SI")
A8: LOS NATIVOS S.A. | B8: =+C8+D8+E8-G8+F8 | C8: =SUMIF(conceptoFijo!$A:$A,A8,conceptoFijo!$J:$J) | D8: =SUMIF(conceptoVariable!$A:$A,Controles!A8,conceptoVariable!$J:$J) | E8: =SUMIF(conceptoMovilidad!$A:$A,A8,conceptoMovilidad!$I:$I) | F8: =SUMIF(conceptoRecuperos!$B:$B,A8,conceptoRecuperos!$J:$J) | G8: =SUMIFS(conceptoAnticipos!$J:$J,conceptoAnticipos!$B:$B,Controles!A8,conceptoAnticipos!$A:$A,"SI")
A9: LLORENTE HNOS SA | B9: =+C9+D9+E9-G9+F9 | C9: =SUMIF(conceptoFijo!$A:$A,A9,conceptoFijo!$J:$J) | D9: =SUMIF(conceptoVariable!$A:$A,Controles!A9,conceptoVariable!$J:$J) | E9: =SUMIF(conceptoMovilidad!$A:$A,A9,conceptoMovilidad!$I:$I) | F9: =SUMIF(conceptoRecuperos!$B:$B,A9,conceptoRecuperos!$J:$J) | G9: =SUMIFS(conceptoAnticipos!$J:$J,conceptoAnticipos!$B:$B,Controles!A9,conceptoAnticipos!$A:$A,"SI")
A10: FINCAS Y BODEGAS MONTECHEZ S.A. | B10: =+C10+D10+E10-G10+F10 | C10: =SUMIF(conceptoFijo!$A:$A,A10,conceptoFijo!$J:$J) | D10: =SUMIF(conceptoVariable!$A:$A,Controles!A10,conceptoVariable!$J:$J) | E10: =SUMIF(conceptoMovilidad!$A:$A,A10,conceptoMovilidad!$I:$I) | F10: =SUMIF(conceptoRecuperos!$B:$B,A10,conceptoRecuperos!$J:$J) | G10: =SUMIFS(conceptoAnticipos!$J:$J,conceptoAnticipos!$B:$B,Controles!A10,conceptoAnticipos!$A:$A,"SI")
A11: TELLERIA JUAN GABRIEL | B11: =+C11+D11+E11-G11+F11 | C11: =SUMIF(conceptoFijo!$A:$A,A11,conceptoFijo!$J:$J) | D11: =SUMIF(conceptoVariable!$A:$A,Controles!A11,conceptoVariable!$J:$J) | E11: =SUMIF(conceptoMovilidad!$A:$A,A11,conceptoMovilidad!$I:$I) | F11: =SUMIF(conceptoRecuperos!$B:$B,A11,conceptoRecuperos!$J:$J) | G11: =SUMIFS(conceptoAnticipos!$J:$J,conceptoAnticipos!$B:$B,Controles!A11,conceptoAnticipos!$A:$A,"SI")
A12: AGRISUS SA | B12: =+C12+D12+E12-G12+F12 | C12: =SUMIF(conceptoFijo!$A:$A,A12,conceptoFijo!$J:$J) | D12: =SUMIF(conceptoVariable!$A:$A,Controles!A12,conceptoVariable!$J:$J) | E12: =SUMIF(conceptoMovilidad!$A:$A,A12,conceptoMovilidad!$I:$I) | F12: =SUMIF(conceptoRecuperos!$B:$B,A12,conceptoRecuperos!$J:$J) | G12: =SUMIFS(conceptoAnticipos!$J:$J,conceptoAnticipos!$B:$B,Controles!A12,conceptoAnticipos!$A:$A,"SI")
B13: =SUM(B2:B12) | C13: =SUM(C2:C12) | D13: =SUM(D2:D12) | E13: =SUM(E2:E12) | F13: =SUM(F2:F12) | G13: =SUM(G2:G12)

Sheet conceptoFijo
A1: t_cliente | B1: t_centroCosto | C1: i_finca | D1: t_alicuota | E1: i_netoGravado | F1: i_descripcion | G1: i_tipoItem | H1: i_unidades | I1: i_cuentaContable | J1: formatoNumero
A2: GRANAR S.A.C y F. | B2: altamira | C2: la peregrina | D2: 0.105 | E2: 1430821,03 | F2: SS FINCA (LN) | G2: Concepto | H2: 1 | I2: 414001001 | J2: =VALUE(E2)
A3: GRANAR S.A.C y F. | B3: altamira | C3: la peregrina | D3: 0.21 | E3: 2382371,71 | F3: SS FINCA (LN) | G3: Concepto | H3: 1 | I3: 414001001 | J3: =VALUE(E3)

Sheet conceptoVariable
A1: t_cliente | B1: t_centroCosto | C1: i_finca | D1: t_alicuota | E1: i_netoGravado | F1: i_descripcion | G1: i_tipoItem | H1: i_unidades | I1: i_cuentaContable | J1: formatoNumero
A2: GRANAR S.A.C y F. | B2: altamira | C2: la peregrina | D2: 0.21 | E2: 4891208,48 | F2: LABORES FINCA (LN) | G2: Concepto | H2: 1 | I2: 414001003 | J2: =VALUE(E2)

Sheet conceptoMovilidad
A1: t_cliente | B1: i_centroCosto | C1: i_alicuota | D1: i_netoGravado | E1: i_descripcion | F1: i_tipoItem | G1: i_unidades | H1: i_cuentaContable | I1: formatoNumero
A2: GRANAR S.A.C y F. | B2: ADM-ADMINISTRACION | C2: IVA (21%) | D2: 592149,04 | E2: SS MOVILIDAD MS-EG-MM (LN) | F2: Concepto | G2: 1 | H2: 414001001 | I2: =VALUE(D2)

Sheet conceptoRecuperos
A1: i_factura | B1: t_cliente | C1: i_centroCosto | D1: i_alicuota | E1: i_netoGravado | F1: i_descripcion | G1: i_tipoItem | H1: i_unidades | I1: i_cuentaContable | J1: formatoNumero
A2: NO | B2: GRANAR S.A.C y F. | C2: 2-MODULO ALTAMIRA | D2: IVA (21%) | F2: AJUSTE ANTICIPO SACSA (LN) | G2: Concepto | H2: 1 | I2: 570101009 | J2: =VALUE(E2)

Sheet conceptoAnticipos
A1: i_anticipo | B1: t_cliente | C1: i_centroCosto | D1: i_alicuota | E1: i_netoGravado | F1: i_descripcion | G1: i_tipoItem | H1: i_unidades | I1: i_cuentaContable | J1: formatoNumero
A2: SI | B2: GRANAR S.A.C y F. | C2: EST-ESTRUCTURA | D2: IVA (21%) | E2: 600000 | F2: ANTICIPO | G2: Descuento | H2: 1 | I2: 570101009 | J2: =VALUE(E2)

Sheet Traductor_iva
A1: t_alicuota | B1: i_iva
A2: 0.105 | B2: IVA (10.5%)
A3: 0.21 | B3: IVA (21%)

Sheet Traductor_centroCosto
A1: t_centroCosto | B1: i_centroCosto
A2: altamira | B2: 2-MODULO ALTAMIRA
A3: ugarteche | B3: 1-MODULO UGARTECHE

Sheet Traductor_cliente
A1: i_cliente | B1: t_cliente
A2: FOA AGUAS DE ALTAMIRA | B2: FOA Aguas de Altamira
A3: FOI TERRUÑOS DE LOS ANDES | B3: FOI TerruÃ±os de los Andes
A4: GRANAR S.A.C y F. | B4: Granar SACyF
A5: LLORENTE HNOS SA | B5: Llorente Hnos SA
A6: LOS NATIVOS S.A. | B6: Los Nativos SA
A7: FINCAS Y BODEGAS MONTECHEZ S.A. | B7: Montechez
A8: FINCA LAS MAGDALENAS S. A. S. | B8: Sona Aldo Guillermo
A9: TELLERIA JUAN GABRIEL | B9: Telleria Juan Gabriel
A10: AGRISUS SA | B10: Agrisus
A11: A & T Y ASOCIADOS SA | B11: AyT
A12: CABALGANDO SAFI | B12: Cabalgando
A13: GRANAR S.A.C y F. | B13: Granar SACyF (AB)

Sheet Padrones
A1: TipoFactura | B1: IVA | C1: CentroCostos | D1: TipoItem
A2: Factura A | B2: IVA (10.5%) | C2: 1-MODULO UGARTECHE | D2: Concepto
A3: Factura A Webservice | B3: IVA (21%) | C3: 2-MODULO ALTAMIRA | D3: Descuento
A4: Factura Crédito Electrónica A | C4: 3-MOVILIDAD MARIANO SAVINA
A5: Factura Crédito Electrónica A Webservice | C5: 4-MOVILIDAD LEANDRO SAVINA
A6: Nota de Crédito A | C6: 5-MOVILIDAD ESTEBAN GAMUNDI
A7: Nota de Crédito A Webservice | C7: 6-FOI TERRUÑOS DE LOS ANDES
C8: 7-TELLERIA
C9: 8-SONA
C10: 9-LLORENTE
C11: 10-GRANAR
C12: 11-LOS NATIVOS
C13: 12-FOA AGUAS DE ALTAMIRA
C14: ADM-ADMINISTRACION
C15: EST-ESTRUCTURA
